monkey/crawler/crawler.py
monkey/crawler/op_codes.py
monkey/crawler/pipeline.py
monkey/crawler/processor.py
monkey/crawler/crawlers/csv.py
monkey/crawler/crawlers/dir.py
monkey/crawler/crawlers/xml.py
monkey/crawler/handlers/bulk.py
monkey/crawler/handlers/calc.py
monkey/crawler/handlers/composite.py
monkey/crawler/handlers/filter.py
monkey/crawler/handlers/format.py
monkey/crawler/handlers/project.py
monkey/crawler/handlers/transform.py
monkey/crawler/processors/dump.py
monkey_crawler-2.0.0.dev10.dist-info/METADATA
monkey_crawler-2.0.0.dev10.dist-info/WHEEL
monkey_crawler-2.0.0.dev10.dist-info/top_level.txt
monkey_crawler-2.0.0.dev10.dist-info/RECORD
