Metadata-Version: 2.4
Name: monkey.crawler
Version: 2.0.0.dev10
Summary: Small framework to crawl misc data sources and process records.
Author-email: Xavier ROY <xavier@regbuddy.eu>
License: Apache License, Version 2.0
Project-URL: Repository, https://bitbucket.org/monkeytechnologies/monkey-crawler
Classifier: Programming Language :: Python
Classifier: Development Status :: 1 - Planning
Classifier: Operating System :: OS Independent
Classifier: Programming Language :: Python :: 3.12
Classifier: Topic :: Software Development :: Libraries :: Python Modules
Classifier: Intended Audience :: Developers
Requires-Python: >=3.12
